papermap/__init__.py
papermap/__main__.py
papermap/cli.py
papermap/geodesy.py
papermap/papermap.py
papermap/py.typed
papermap/tile.py
papermap/tile_provider.py
papermap/tile_providers/__init__.py
papermap/tile_providers/basemap_at.py
papermap/tile_providers/cartodb.py
papermap/tile_providers/cyclosm.py
papermap/tile_providers/esri.py
papermap/tile_providers/google.py
papermap/tile_providers/here.py
papermap/tile_providers/jawg.py
papermap/tile_providers/maptiler.py
papermap/tile_providers/misc.py
papermap/tile_providers/nasagibs.py
papermap/tile_providers/nlmaps.py
papermap/tile_providers/openseamap.py
papermap/tile_providers/openstreetmap.py
papermap/tile_providers/opentopomap.py
papermap/tile_providers/stadia.py
papermap/tile_providers/swiss.py
papermap/tile_providers/thunderforest.py
papermap/tile_providers/tomtom.py
papermap/tile_providers/usgs.py
papermap/tile_providers/wikimedia.py
papermap/utils.py
papermap-2026.1.0.dist-info/WHEEL
papermap-2026.1.0.dist-info/entry_points.txt
papermap-2026.1.0.dist-info/METADATA
papermap-2026.1.0.dist-info/RECORD
