Metadata-Version: 2.3
Name: papermap
Version: 2026.1.0
Summary: papermap is a Python library and CLI tool for creating ready-to-print paper maps.
Keywords: map,maps,paper,cartography,openstreetmap,osm,topography,geodesy,utm,topography,mgrs
Author: Steven van de Graaf
Author-email: Steven van de Graaf <steven@vandegraaf.xyz>
License: *papermap*
Classifier: Development Status :: 4 - Beta
Classifier: Intended Audience :: Developers
Classifier: License :: OSI Approved :: GNU General Public License v3 or later (GPLv3+)
Classifier: Operating System :: OS Independent
Classifier: Programming Language :: Python
Classifier: Programming Language :: Python :: 3
Classifier: Programming Language :: Python :: 3.11
Classifier: Programming Language :: Python :: 3.12
Classifier: Programming Language :: Python :: 3.13
Classifier: Programming Language :: Python :: 3.14
Classifier: Typing :: Typed
Requires-Dist: click
Requires-Dist: click-default-group
Requires-Dist: fpdf2
Requires-Dist: httpx
Requires-Dist: pillow
Requires-Python: >=3.11, <4
Project-URL: Documentation, https://papermap.readthedocs.io/en/stable/
Project-URL: Changelog, https://papermap.readthedocs.io/en/stable/changelog.html
Project-URL: Source code, https://github.com/sgraaf/papermap
Project-URL: Issues, https://github.com/sgraaf/papermap/issues
